src/Main.py
src/Utils.py
src/__init__.py
src/__main__.py
voice_assistant_linux-0.0.5.dist-info/LICENSE
voice_assistant_linux-0.0.5.dist-info/METADATA
voice_assistant_linux-0.0.5.dist-info/WHEEL
voice_assistant_linux-0.0.5.dist-info/top_level.txt
voice_assistant_linux-0.0.5.dist-info/RECORD
