Metadata-Version: 2.1
Name: voice-assistant-linux
Version: 0.0.5
Summary: Virtual assistant from voice commands to control operating system graphical user interface.
Home-page: https://github.com/henrikbeck95/voice_assistant_linux/
Author: Henrik Beck
Author-email: henrikbeck95@gmail.com
License: GPL3
Keywords: val,voice assistant,i3wm,Unix Shell
Platform: UNKNOWN
Classifier: Development Status :: 3 - Alpha
Classifier: Intended Audience :: Developers
Classifier: Programming Language :: Python :: 3
Classifier: Operating System :: POSIX :: Linux
Requires-Python: >=3.10
License-File: LICENSE
Requires-Dist: SpeechRecognition
Requires-Dist: yaml-1.3
